README.md
setup.py
hr_prometheus/__init__.py
hr_prometheus/middleware.py
hr_prometheus/monitors.py
hr_prometheus/view.py
hr_prometheus.egg-info/PKG-INFO
hr_prometheus.egg-info/SOURCES.txt
hr_prometheus.egg-info/dependency_links.txt
hr_prometheus.egg-info/requires.txt
hr_prometheus.egg-info/top_level.txt