Metadata-Version: 2.1
Name: hr-prometheus
Version: 0.1.1
Summary: Prometheus integration for aiohttp framework.
Home-page: https://github.com/hundredrooms/hr-prometheus
Author: Mateu Cànaves
Author-email: mcanaves@hundredrooms.com
License: BSD
Platform: UNKNOWN
Classifier: Development Status :: 3 - Alpha
Classifier: Environment :: Web Environment
Classifier: Intended Audience :: Developers
Classifier: License :: OSI Approved :: BSD License
Classifier: Operating System :: OS Independent
Classifier: Topic :: Internet :: WWW/HTTP
Classifier: Programming Language :: Python :: 3
Classifier: Programming Language :: Python :: 3.6
Classifier: Programming Language :: Python :: 3.7
